pyramid_task_scheduler/__init__.py
pyramid_task_scheduler-0.0.4.dist-info/LICENSE
pyramid_task_scheduler-0.0.4.dist-info/METADATA
pyramid_task_scheduler-0.0.4.dist-info/WHEEL
pyramid_task_scheduler-0.0.4.dist-info/top_level.txt
pyramid_task_scheduler-0.0.4.dist-info/RECORD
