Metadata-Version: 2.1
Name: pyramid-task-scheduler
Version: 0.0.4
Summary: task scheduler for pyramid framework
Author-email: Patrick Magyar <magyarpatrick@gmail.com>
License: MIT License Copyright (c) <year> <copyright holders>        
Project-URL: Homepage, https://github.com/Eldhrimner/pyramid_task_scheduler
Project-URL: Bug Tracker, https://github.com/Eldhrimner/pyramid_task_scheduler/issues
Classifier: Development Status :: 2 - Pre-Alpha
Classifier: Programming Language :: Python :: 3
Classifier: Framework :: Pyramid
Classifier: License :: OSI Approved :: MIT License
Classifier: Operating System :: POSIX :: Linux
Requires-Python: >=3.6
License-File: LICENSE
Requires-Dist: apscheduler
Requires-Dist: docutils
Requires-Dist: waitress
Requires-Dist: watchdog
Requires-Dist: wheel
